haphazard/__init__.py
haphazard/data/__init__.py
haphazard/data/base_dataset.py
haphazard/data/mask.py
haphazard/data/datasets/__init__.py
haphazard/data/datasets/a8a/__init__.py
haphazard/data/datasets/dry_bean/__init__.py
haphazard/data/datasets/dummy_dataset/__init__.py
haphazard/data/datasets/gas/__init__.py
haphazard/data/datasets/higgs/__init__.py
haphazard/data/datasets/imdb/__init__.py
haphazard/data/datasets/magic04/__init__.py
haphazard/data/datasets/susy/__init__.py
haphazard/models/__init__.py
haphazard/models/base_model.py
haphazard/models/model_zoo/__init__.py
haphazard/models/model_zoo/dummy_model/__init__.py
haphazard/models/model_zoo/dynfo/__init__.py
haphazard/models/model_zoo/dynfo/dynfo.py
haphazard/models/model_zoo/fae/__init__.py
haphazard/models/model_zoo/fae/fae.py
haphazard/models/model_zoo/haptransformer/__init__.py
haphazard/models/model_zoo/haptransformer/haptransformer.py
haphazard/models/model_zoo/haptransformer/set_transformer/modules.py
haphazard/models/model_zoo/hi2/__init__.py
haphazard/models/model_zoo/hi2/hi2.py
haphazard/models/model_zoo/hi2/Utils/utils.py
haphazard/models/model_zoo/nb3/__init__.py
haphazard/models/model_zoo/nb3/nb3.py
haphazard/models/model_zoo/ocds/__init__.py
haphazard/models/model_zoo/ocds/ocds.py
haphazard/models/model_zoo/olifl/__init__.py
haphazard/models/model_zoo/olifl/olifl.py
haphazard/models/model_zoo/olvf/__init__.py
haphazard/models/model_zoo/olvf/olvf.py
haphazard/models/model_zoo/orf3v/__init__.py
haphazard/models/model_zoo/orf3v/orf3v.py
haphazard/models/model_zoo/ovfm/__init__.py
haphazard/models/model_zoo/ovfm/ovfm.py
haphazard/models/model_zoo/ovfm/OVFM/source/cap_main.py
haphazard/models/model_zoo/ovfm/OVFM/source/tra_main.py
haphazard/models/model_zoo/ovfm/OVFM/source/em/embody.py
haphazard/models/model_zoo/ovfm/OVFM/source/em/expectation_maximization.py
haphazard/models/model_zoo/ovfm/OVFM/source/em/online_expectation_maximization.py
haphazard-1.1.3.dist-info/licenses/LICENSE
haphazard-1.1.3.dist-info/METADATA
haphazard-1.1.3.dist-info/WHEEL
haphazard-1.1.3.dist-info/top_level.txt
haphazard-1.1.3.dist-info/RECORD
