Metadata-Version: 2.4
Name: haphazard
Version: 1.1.3
Summary: A modular framework for registering and running haphazard datasets and models.
Home-page: https://github.com/theArijitDas/Haphazard-Package/
Author: Arijit Das
Author-email: dasarijitjnv@gmail.com
License: MIT
Project-URL: Bug Tracker, https://github.com/theArijitDas/Haphazard-Package/issues
Project-URL: Source Code, https://github.com/theArijitDas/Haphazard-Package/
Keywords: machine-learning haphazard models datasets registration framework
Classifier: Development Status :: 3 - Alpha
Classifier: Intended Audience :: Developers
Classifier: Programming Language :: Python :: 3
Classifier: Programming Language :: Python :: 3.10
Classifier: License :: OSI Approved :: MIT License
Classifier: Operating System :: OS Independent
Classifier: Topic :: Software Development :: Libraries :: Python Modules
Classifier: Topic :: Scientific/Engineering :: Artificial Intelligence
Requires-Python: >=3.10
License-File: LICENSE
Requires-Dist: numpy
Requires-Dist: pandas
Requires-Dist: tqdm
Requires-Dist: scikit-learn
Requires-Dist: torch
Requires-Dist: statsmodels
Provides-Extra: orf3v
Requires-Dist: tdigest; extra == "orf3v"
Provides-Extra: hi2
Requires-Dist: Pillow; extra == "hi2"
Requires-Dist: matplotlib; extra == "hi2"
Requires-Dist: torchvision; extra == "hi2"
Requires-Dist: timm; extra == "hi2"
Provides-Extra: all
Requires-Dist: tdigest; extra == "all"
Requires-Dist: Pillow; extra == "all"
Requires-Dist: matplotlib; extra == "all"
Requires-Dist: torchvision; extra == "all"
Requires-Dist: timm; extra == "all"
Dynamic: author
Dynamic: author-email
Dynamic: classifier
Dynamic: description
Dynamic: description-content-type
Dynamic: home-page
Dynamic: keywords
Dynamic: license
Dynamic: license-file
Dynamic: project-url
Dynamic: provides-extra
Dynamic: requires-dist
Dynamic: requires-python
Dynamic: summary
